karya/__init__.py
karya/__main__.py
karya/cli.py
karya/utils/__init__.py
karya/utils/args_parser.py
karya/utils/config.py
karya/utils/file.py
karya-0.0.1.dist-info/METADATA
karya-0.0.1.dist-info/WHEEL
karya-0.0.1.dist-info/entry_points.txt
karya-0.0.1.dist-info/top_level.txt
karya-0.0.1.dist-info/RECORD
