Metadata-Version: 2.1
Name: karya
Version: 0.0.1
Summary: A CLI application for karya (usekarya.com).
Author-email: Udit Juneja <support@usekarya.com>
Requires-Dist: click ==8.1.7
Requires-Dist: gitdb ==4.0.10
Requires-Dist: GitPython ==3.1.37
Requires-Dist: pathspec ==0.11.2
Requires-Dist: python-slugify ==8.0.1
Requires-Dist: smmap ==5.0.1
Requires-Dist: text-unidecode ==1.3
Requires-Dist: PyYAML ==6.0.1
Requires-Dist: requests ==2.31.0
